mixsim/__init__.py
mixsim/conf_schema.py
mixsim/constants.py
mixsim/pipeline.py
mixsim/config/__init__.py
mixsim/config/argparsing.py
mixsim/config/cfgparsing.py
mixsim/config/fields.py
mixsim/config/help_formatter.py
mixsim/config/options.py
mixsim/config/utils.py
mixsim/config/parsers/__init__.py
mixsim/config/parsers/config_parsers.py
mixsim/config/parsers/decoding.py
mixsim/config/parsers/encoding.py
mixsim/config/parsers/registry_utils.py
mixsim/config/wrappers/__init__.py
mixsim/config/wrappers/dataclass_wrapper.py
mixsim/config/wrappers/docstring.py
mixsim/config/wrappers/field_metavar.py
mixsim/config/wrappers/field_wrapper.py
mixsim/config/wrappers/wrapper.py
mixsim/dataloaders/__init__.py
mixsim/dataloaders/base_dataloader.py
mixsim/dataloaders/source_dataloader.py
mixsim/dataloaders/wsj0_dataloader.py
mixsim/dataloaders/wsj0_preprocessing.py
mixsim/mixer/__init__.py
mixsim/mixer/base_mixer.py
mixsim/mixer/multi_channel_mixer.py
mixsim/rir_simulator/__init__.py
mixsim/rir_simulator/base_rir_simulator.py
mixsim/rir_simulator/pyroomacoustics_generator.py
mixsim/rir_simulator/room.py
mixsim/rir_simulator/source.py
mixsim/trajectory_generator/__init__.py
mixsim/trajectory_generator/base_generator.py
mixsim/trajectory_generator/curve_generator.py
mixsim/trajectory_generator/curved_quadrilateral_generator.py
mixsim/trajectory_generator/line_generator.py
mixsim/trajectory_generator/quadrilateral_generator.py
mixsim/trajectory_generator/region_2d.py
mixsim/trajectory_generator/static_generator.py
mixsim/util/__init__.py
mixsim/util/audio.py
mixsim/util/normalization.py
mixsim/util/utils.py
mixsim/util/visulization.py
mixsim/util/example_data/clean.wav
mixsim-0.3.0.dist-info/entry_points.txt
mixsim-0.3.0.dist-info/LICENSE
mixsim-0.3.0.dist-info/WHEEL
mixsim-0.3.0.dist-info/METADATA
mixsim-0.3.0.dist-info/RECORD
