Metadata-Version: 2.1
Name: mixsim
Version: 0.3.0
Summary: An open-source dataset for multiple purposes, such as speaker localization/tracking, dereverberation, enhancement, separation, and recognition.
Keywords: open-source dataset,multiple purposes,speaker localization/tracking,dereverberation,enhancement,separation,recognition
Author-email: HAO Xiang <haoxiangsnr@gmail.com>
Requires-Python: >=3.10
Classifier: Programming Language :: Python :: 3.10
Classifier: Development Status :: 2 - Pre-Alpha
Classifier: License :: OSI Approved :: MIT License
Classifier: Environment :: GPU :: NVIDIA CUDA
Classifier: Operating System :: OS Independent
Requires-Dist: webrtcvad
Requires-Dist: numpy
Requires-Dist: scipy
Requires-Dist: matplotlib
Requires-Dist: geomdl
Requires-Dist: joblib
Requires-Dist: librosa
Requires-Dist: pyroomacoustics
Requires-Dist: soundfile
Requires-Dist: toml
Requires-Dist: tqdm
Requires-Dist: pydantic
Requires-Dist: typing_inspect
Requires-Dist: flit ; extra == "build"
Requires-Dist: python-semantic-release ; extra == "build"
Requires-Dist: sphinx-rtd-theme ; extra == "docs"
Requires-Dist: myst-nb ; extra == "docs"
Requires-Dist: autodoc_pydantic ; extra == "docs"
Requires-Dist: pytest ; extra == "test"
Requires-Dist: pytest-cov ; extra == "test"
Project-URL: Documentation, https://mixsim.readthedocs.io/en/latest/
Project-URL: Source, https://github.com/haoxiangsnr/mixsim
Provides-Extra: build
Provides-Extra: docs
Provides-Extra: test
